cleavenet/__init__.py
cleavenet/analysis.py
cleavenet/data.py
cleavenet/models.py
cleavenet/plotter.py
cleavenet/utils.py
cleavenet-0.1.2.dist-info/LICENSE
cleavenet-0.1.2.dist-info/METADATA
cleavenet-0.1.2.dist-info/WHEEL
cleavenet-0.1.2.dist-info/top_level.txt
cleavenet-0.1.2.dist-info/RECORD
