Metadata-Version: 2.1
Name: cleavenet
Version: 0.1.2
Summary: Deep learning model for substrate cleavage prediction and generation
Home-page: https://github.com/microsoft/cleavenet
License: BSD 2-clause
Classifier: Programming Language :: Python :: 3
Classifier: License :: OSI Approved :: MIT License
Classifier: Operating System :: OS Independent
Requires-Python: >=3.6
License-File: LICENSE
Requires-Dist: jellyfish==1.1.3
Requires-Dist: logomaker==0.8.6
Requires-Dist: matplotlib==3.10.0
Requires-Dist: numpy
Requires-Dist: pandas==2.2.3
Requires-Dist: scikit-learn==1.6.1
Requires-Dist: scipy==1.15.1
Requires-Dist: seaborn==0.13.2
Requires-Dist: setuptools==75.8.0
Requires-Dist: tensorflow==2.18.0
Requires-Dist: tqdm==4.67.1
